<?xml version="1.0" encoding="UTF-8"?>
<crear>
    <test>
        <nombre_formulario>Test</nombre_formulario>
        <se_envia>POST</se_envia>
        <tipo_de_servicio>SOAP</tipo_de_servicio>
        <se_guardara_en>MySQL</se_guardara_en>
        <usuario>
            <que_quieres>Caja</que_quieres>
            <como_se_llama>Usuario</como_se_llama>
            <que_dato_recibira>texto</que_dato_recibira>
            <es_obligatorio>si</es_obligatorio>
            <longitud_minima_es>5</longitud_minima_es>
            <longitud_maxima_es>10</longitud_maxima_es>
            <mensaje_de_error_es_obligatorio>Ey! Se te olvido</mensaje_de_error_es_obligatorio>
            <mensaje_de_error_longitud_minima>Muy corto, minimo 5</mensaje_de_error_longitud_minima>
            <mensaje_de_error_longitud_maxima>Te pasaste</mensaje_de_error_longitud_maxima>
        </usuario>
        <correo>
            <que_quieres>Caja</que_quieres>
            <como_se_llama>Correo</como_se_llama>
            <que_dato_recibira>correo</que_dato_recibira>
            <mensaje_de_error_tipo_dato>Por favor digita un correo valido</mensaje_de_error_tipo_dato>
            <es_obligatorio>si</es_obligatorio>
            <longitud_minima_es>10</longitud_minima_es>
            <longitud_maxima_es>20</longitud_maxima_es>
            <mensaje_de_error_longitud_minima>Al menos 10</mensaje_de_error_longitud_minima>
        </correo>
        <genero>
            <que_quieres>Circulo</que_quieres>
            <como_se_llama>Genero</como_se_llama>
            <que_dato_recibira>texto</que_dato_recibira>
            <es_obligatorio>si</es_obligatorio>
            <longitud_maxima_es>2</longitud_maxima_es>
            <posibles_valores>F=Mujer,M=Hombre</posibles_valores>
        </genero>
        <pais>
            <que_quieres>Listado</que_quieres>
            <como_se_llama>Pais</como_se_llama>
            <que_dato_recibira>numero</que_dato_recibira>
            <mensaje_de_error_tipo_dato>Selecciona un pais</mensaje_de_error_tipo_dato>
            <es_obligatorio>si</es_obligatorio>
            <mensaje_de_error_es_obligatorio>y el pais?</mensaje_de_error_es_obligatorio>
            <posibles_valores>paises::nombre</posibles_valores>
        </pais>
        <gusto>
            <que_quieres>Listado</que_quieres>
            <como_se_llama>Me gusta</como_se_llama>
            <que_dato_recibira>numero</que_dato_recibira>
            <es_obligatorio>si</es_obligatorio>
            <posibles_valores>1=Bailar, 2=Cantar</posibles_valores>
        </gusto>
        <recibir_publicidad>
            <que_quieres>Cuadrado</que_quieres>
            <como_se_llama>Recibir publicidad</como_se_llama>
            <que_dato_recibira>numero</que_dato_recibira>
            <es_obligatorio>no</es_obligatorio>
            <posibles_valores>1=Si</posibles_valores>
        </recibir_publicidad>
        <fecha>
            <que_quieres>Caja</que_quieres>
            <como_se_llama>Fecha</como_se_llama>
            <que_dato_recibira>fecha</que_dato_recibira>
            <es_obligatorio>si</es_obligatorio>
        </fecha>
        <clave>
            <que_quieres>Caja</que_quieres>
            <como_se_llama>Clave</como_se_llama>
            <que_dato_recibira>clave</que_dato_recibira>
            <es_obligatorio>si</es_obligatorio>
            <longitud_maxima_es>15</longitud_maxima_es>
            <mensaje_de_error_es_obligatorio>Y la seguridad...</mensaje_de_error_es_obligatorio>
        </clave>
        <observaciones>
            <que_quieres>Caja</que_quieres>
            <como_se_llama>Observaciones</como_se_llama>
            <que_dato_recibira>mucho texto</que_dato_recibira>
            <es_obligatorio>no</es_obligatorio>
            <longitud_maxima_es>100</longitud_maxima_es>
        </observaciones>
        <enviar>
            <que_quieres>Agregar</que_quieres>
            <como_se_llama>Enviar</como_se_llama>
        </enviar>
        <encontrar>
            <que_quieres>Buscar</que_quieres>
            <como_se_llama>Encontrar</como_se_llama>
        </encontrar>
        <actualizar>
            <que_quieres>Modificar</que_quieres>
            <como_se_llama>Actualizar</como_se_llama>
        </actualizar>
        <eliminar>
            <que_quieres>Borrar</que_quieres>
            <como_se_llama>Eliminar</como_se_llama>
        </eliminar>
        <volver>
            <que_quieres>Cancelar</que_quieres>
            <como_se_llama>Volver</como_se_llama>
        </volver>
        <resetear>
            <que_quieres>Limpiar</que_quieres>
            <como_se_llama>Resetear</como_se_llama>
        </resetear>
    </test>
</crear>